CHANGELOG.md
LICENSE.txt
MANIFEST.in
README.md
main.py
requirements.txt
setup.py
app_cwebp/Readme-mux.txt
app_cwebp/Readme.txt
batchexec/__init__.py
batchexec.egg-info/PKG-INFO
batchexec.egg-info/SOURCES.txt
batchexec.egg-info/dependency_links.txt
batchexec.egg-info/top_level.txt
venv/Lib/site-packages/_black_version.py
venv/Lib/site-packages/appdirs.py
venv/Lib/site-packages/autopep8.py
venv/Lib/site-packages/easy_install.py
venv/Lib/site-packages/mccabe.py
venv/Lib/site-packages/mypy_extensions.py
venv/Lib/site-packages/pycodestyle.py
venv/Lib/site-packages/pyparsing.py
venv/Lib/site-packages/six.py
venv/Lib/site-packages/typing_extensions.py
venv/Lib/site-packages/Pygments-2.8.0.dist-info/entry_points.txt
venv/Lib/site-packages/Pygments-2.8.0.dist-info/top_level.txt
venv/Lib/site-packages/appdirs-1.4.4.dist-info/LICENSE.txt
venv/Lib/site-packages/appdirs-1.4.4.dist-info/top_level.txt
venv/Lib/site-packages/autopep8-1.5.5.dist-info/entry_points.txt
venv/Lib/site-packages/autopep8-1.5.5.dist-info/top_level.txt
venv/Lib/site-packages/black/__init__.py
venv/Lib/site-packages/black/__main__.py
venv/Lib/site-packages/black-20.8b1.dist-info/entry_points.txt
venv/Lib/site-packages/black-20.8b1.dist-info/top_level.txt
venv/Lib/site-packages/black_primer/cli.py
venv/Lib/site-packages/black_primer/lib.py
venv/Lib/site-packages/blackd/__init__.py
venv/Lib/site-packages/bleach/__init__.py
venv/Lib/site-packages/bleach/callbacks.py
venv/Lib/site-packages/bleach/html5lib_shim.py
venv/Lib/site-packages/bleach/linkifier.py
venv/Lib/site-packages/bleach/sanitizer.py
venv/Lib/site-packages/bleach/utils.py
venv/Lib/site-packages/bleach-3.3.0.dist-info/top_level.txt
venv/Lib/site-packages/bleach/_vendor/__init__.py
venv/Lib/site-packages/bleach/_vendor/vendor.txt
venv/Lib/site-packages/bleach/_vendor/Django-1.11.29.dist-info/entry_points.txt
venv/Lib/site-packages/bleach/_vendor/Django-1.11.29.dist-info/top_level.txt
venv/Lib/site-packages/bleach/_vendor/django/__init__.py
venv/Lib/site-packages/bleach/_vendor/django/core/__init__.py
venv/Lib/site-packages/bleach/_vendor/django/core/validators.py
venv/Lib/site-packages/bleach/_vendor/html5lib/__init__.py
venv/Lib/site-packages/bleach/_vendor/html5lib/_ihatexml.py
venv/Lib/site-packages/bleach/_vendor/html5lib/_inputstream.py
venv/Lib/site-packages/bleach/_vendor/html5lib/_tokenizer.py
venv/Lib/site-packages/bleach/_vendor/html5lib/_utils.py
venv/Lib/site-packages/bleach/_vendor/html5lib/constants.py
venv/Lib/site-packages/bleach/_vendor/html5lib/html5parser.py
venv/Lib/site-packages/bleach/_vendor/html5lib/serializer.py
venv/Lib/site-packages/bleach/_vendor/html5lib-1.1.dist-info/top_level.txt
venv/Lib/site-packages/bleach/_vendor/html5lib/_trie/__init__.py
venv/Lib/site-packages/bleach/_vendor/html5lib/_trie/_base.py
venv/Lib/site-packages/bleach/_vendor/html5lib/_trie/py.py
venv/Lib/site-packages/certifi-2020.12.5.dist-info/top_level.txt
venv/Lib/site-packages/chardet-4.0.0.dist-info/entry_points.txt
venv/Lib/site-packages/chardet-4.0.0.dist-info/top_level.txt
venv/Lib/site-packages/click-7.1.2.dist-info/top_level.txt
venv/Lib/site-packages/colorama-0.4.4.dist-info/LICENSE.txt
venv/Lib/site-packages/colorama-0.4.4.dist-info/top_level.txt
venv/Lib/site-packages/docutils-0.16.dist-info/COPYING.txt
venv/Lib/site-packages/docutils-0.16.dist-info/top_level.txt
venv/Lib/site-packages/flake8-3.8.4.dist-info/entry_points.txt
venv/Lib/site-packages/flake8-3.8.4.dist-info/top_level.txt
venv/Lib/site-packages/idna-2.10.dist-info/top_level.txt
venv/Lib/site-packages/keyring-22.0.1.dist-info/entry_points.txt
venv/Lib/site-packages/keyring-22.0.1.dist-info/top_level.txt
venv/Lib/site-packages/mccabe-0.6.1.dist-info/entry_points.txt
venv/Lib/site-packages/mccabe-0.6.1.dist-info/top_level.txt
venv/Lib/site-packages/mypy_extensions-0.4.3.dist-info/top_level.txt
venv/Lib/site-packages/packaging-20.9.dist-info/top_level.txt
venv/Lib/site-packages/pathspec-0.8.1.dist-info/top_level.txt
venv/Lib/site-packages/pip-20.2.3.dist-info/LICENSE.txt
venv/Lib/site-packages/pip-20.2.3.dist-info/entry_points.txt
venv/Lib/site-packages/pip-20.2.3.dist-info/top_level.txt
venv/Lib/site-packages/pkginfo-1.7.0.dist-info/LICENSE.txt
venv/Lib/site-packages/pkginfo-1.7.0.dist-info/entry_points.txt
venv/Lib/site-packages/pkginfo-1.7.0.dist-info/top_level.txt
venv/Lib/site-packages/pycodestyle-2.6.0.dist-info/entry_points.txt
venv/Lib/site-packages/pycodestyle-2.6.0.dist-info/namespace_packages.txt
venv/Lib/site-packages/pycodestyle-2.6.0.dist-info/top_level.txt
venv/Lib/site-packages/pyflakes-2.2.0.dist-info/entry_points.txt
venv/Lib/site-packages/pyflakes-2.2.0.dist-info/top_level.txt
venv/Lib/site-packages/pyparsing-2.4.7.dist-info/top_level.txt
venv/Lib/site-packages/pywin32_ctypes-0.2.0.dist-info/LICENSE.txt
venv/Lib/site-packages/pywin32_ctypes-0.2.0.dist-info/top_level.txt
venv/Lib/site-packages/readme_renderer-28.0.dist-info/entry_points.txt
venv/Lib/site-packages/readme_renderer-28.0.dist-info/top_level.txt
venv/Lib/site-packages/regex-2020.11.13.dist-info/LICENSE.txt
venv/Lib/site-packages/regex-2020.11.13.dist-info/top_level.txt
venv/Lib/site-packages/requests-2.25.1.dist-info/top_level.txt
venv/Lib/site-packages/requests_toolbelt-0.9.1.dist-info/top_level.txt
venv/Lib/site-packages/rfc3986-1.4.0.dist-info/top_level.txt
venv/Lib/site-packages/setuptools-49.2.1.dist-info/dependency_links.txt
venv/Lib/site-packages/setuptools-49.2.1.dist-info/entry_points.txt
venv/Lib/site-packages/setuptools-49.2.1.dist-info/top_level.txt
venv/Lib/site-packages/six-1.15.0.dist-info/top_level.txt
venv/Lib/site-packages/toml-0.10.2.dist-info/top_level.txt
venv/Lib/site-packages/tqdm-4.56.2.dist-info/entry_points.txt
venv/Lib/site-packages/tqdm-4.56.2.dist-info/top_level.txt
venv/Lib/site-packages/twine-3.3.0.dist-info/entry_points.txt
venv/Lib/site-packages/twine-3.3.0.dist-info/top_level.txt
venv/Lib/site-packages/typed_ast-1.4.2.dist-info/top_level.txt
